walkman/__init__.py
walkman/__main__.py
walkman/audio.py
walkman/backends.py
walkman/boot.py
walkman/channel_mappings.py
walkman/constants.py
walkman/cues.py
walkman/logging.py
walkman/mixins.py
walkman/parsers.py
walkman/sequencers.py
walkman/tests.py
walkman/ui.py
walkman/unit_tests.py
walkman/utilities.py
walkman/version.py
walkman/modules/__init__.py
walkman/modules/base.py
walkman/modules/buildins.py
audiowalkman-0.21.0.dist-info/LICENSE
audiowalkman-0.21.0.dist-info/METADATA
audiowalkman-0.21.0.dist-info/WHEEL
audiowalkman-0.21.0.dist-info/entry_points.txt
audiowalkman-0.21.0.dist-info/top_level.txt
audiowalkman-0.21.0.dist-info/RECORD
