Metadata-Version: 2.1
Name: audiowalkman
Version: 0.21.0
Summary: play audio files in performance contexts
Author: Levin Eric Zimmermann
Author-email: levin.eric.zimmermann@posteo.eu
License: GPL
Requires-Python: >=3.10
License-File: LICENSE
Requires-Dist: pyo (>=1.0.3)
Requires-Dist: PySimpleGUI (<5.0.0,>=4.59.0)
Requires-Dist: click (<9.0.0,>=8.1.3)
Requires-Dist: tomli (<3.0.0,>=2.0.1)
Requires-Dist: jinja2 (<4.0.0,>=3.1.2)
Provides-Extra: testing
Requires-Dist: pytest ; extra == 'testing'
